Metadata-Version: 2.1
Name: SimplePythonGame
Version: 1.4
Summary: A Simple Python Game!
Home-page: https://github.com/SForces/TimePrint
Author: Osman TUNA
Author-email: osmntn08@gmail.com
License: MIT
Classifier: Development Status :: 3 - Alpha
Classifier: Intended Audience :: Developers
Classifier: License :: OSI Approved :: MIT License
Classifier: Programming Language :: Python :: 3.9
Requires-Dist: requests
Requires-Dist: beautifulsoup4
Requires-Dist: TimePrintOnPyPI
